qywx_toolkit/__init__.py
qywx_toolkit/client.py
qywx_toolkit-0.1.1.dist-info/licenses/LICENSE
qywx_toolkit-0.1.1.dist-info/METADATA
qywx_toolkit-0.1.1.dist-info/WHEEL
qywx_toolkit-0.1.1.dist-info/top_level.txt
qywx_toolkit-0.1.1.dist-info/RECORD
