Metadata-Version: 2.4
Name: qywx-toolkit
Version: 0.1.1
Summary: 企业微信纯 requests 工具集
Home-page: https://github.com/yourname/qywx-toolkit
Author: chouhong
Author-email: chouhong2021@163.com
License: MIT
Classifier: Programming Language :: Python :: 3
Classifier: License :: OSI Approved :: MIT License
Classifier: Operating System :: OS Independent
Requires-Python: >=3.7
License-File: LICENSE
Requires-Dist: requests>=2.20
Dynamic: license-file
